{
    "name":"Memory App"
    "icons": [
        {
            "src":"Charmander.png",
            "sizes":"144x144",
            "type":"image/png"
        },
        {
            "src":"Squirtle.png",
            "sizes":"144x144",
            "type":"image/png"
        },
        {
            "src":"Bulbasaur.png",
            "sizes":"144x144",
            "type":"image/png"
        },
        {
            "src":"Cyndaquil.png",
            "sizes":"144x144",
            "type":"image/png"
        },
        {
            "src":"Totodile.png",
            "sizes":"144x144",
            "type":"image/png"
        },
        {
            "src":"Chikorita.png",
            "sizes":"144x144",
            "type":"image/png"
        },
        {
            "src":"Torchic.png",
            "sizes":"144x144",
            "type":"image/png"
        },
        {
            "src":"Mudkip.png",
            "sizes":"144x144",
            "type":"image/png"
        },
        {
            "src":"Treecko.png",
            "sizes":"144x144",
            "type":"image/png"
        },
        {
            "src":"Eevee.png",
            "sizes":"144x144",
            "type":"image/png"
        },
        {
            "src":"Pikachu.png",
            "sizes":"144x144",
            "type":"image/png"
        },
        {
            "src":"Mew.png",
            "sizes":"144x144",
            "type":"image/png"
        }
    ],
    "theme-color":"#9E9E9E",
    "background-color":"#BFDAE9",
    "scope":"xxxx/memory_game_app",
    "start-url":"xxxx/memory_game_app/index.html",
    "display":"stand-alone",
    "orientation":"portrait"
}